{
  "jobTitle": "Trainee - Software Developer",
  "companyName": "Circular Angle Private Limited",
  "jobLocation": "Thane West",
  "jobDescription": "Develop and maintain .Net applications, work with project managers to determine needs and apply/customize existing technology, support multiple projects and deadlines, document work progress.",
  "requiredSkills": [
    ".NET",
    "ASP.NET",
    "ADO.NET",
    ".Net Core",
    "MVC",
    "C#",
    "Web API",
    "Angular",
    "React",
    "HTML",
    "CSS",
    "JavaScript",
    "AJAX",
    "LINQ",
    "Bootstrap",
    "Entity Framework",
    "JQuery",
    "SQL Server",
    "Stored procedures"
  ],
  "preferredQualifications": [],
  "salaryRange": null,
  "jobType": null,
  "gpaCriteria": null,
  "experienceLevel": "Entry-level",
  "applicationDeadline": null,
  "benefitsOffered": [],
  "workModel": "On-site"
}